README.md
setup.py
cnslib/__init__.py
cnslib/agent.py
cnslib/argtypes.py
cnslib/genepool.py
cnslib/genome.py
cnslib/population.py
cnslib/scoreboard.py
cnslib/optimizers/__init__.py
cnslib/optimizers/base.py
cnslib/optimizers/genepool_async.py
cnslib/optimizers/score_sync.py
pytorch_cns.egg-info/PKG-INFO
pytorch_cns.egg-info/SOURCES.txt
pytorch_cns.egg-info/dependency_links.txt
pytorch_cns.egg-info/requires.txt
pytorch_cns.egg-info/top_level.txt