Metadata-Version: 1.0
Name: pytorch-cns
Version: 0.3.1
Summary: Generalized Compressed Network Search with PyTorch
Home-page: https://github.com/awentzonline/pytorch-cns
Author: Adam Wentz
Author-email: adam@adamwentz.com
License: UNKNOWN
Platform: UNKNOWN
